dms_app/__init__.py
dms_app/config.py
dms_app/namespace.py
dms_app/response_helper.py
dms_app/db/__init__.py
dms_app/db/db_connection.py
dms_app/resources/__init__.py
dms_app/resources/access_token/__init__.py
dms_app/resources/access_token/access_token.py
dms_app/resources/add_profile/__init__.py
dms_app/resources/add_profile/add_profile.py
dms_app/resources/add_profile/search_person.py
dms_app/resources/driver_functions/__init__.py
dms_app/resources/driver_functions/fingerprint_user.py
dms_app/resources/fingerprint/__init__.py
dms_app/resources/fingerprint/finger_print.py
dms_app/resources/fingerprint/finger_puser.py
dms_app/resources/fingerprint/tezt.py
dms_app/resources/login_register/__init__.py
dms_app/resources/login_register/login.py
dms_app/resources/login_register/logout.py
dms_app/resources/login_register/super_login.py
dms_app/resources/roles_privileges/__init__.py
dms_app/resources/roles_privileges/role_privileges.py
dms_app/resources/roles_privileges/role_privileges_back.py
dms_app/resources/schema/__init__.py
dms_app/resources/schema/schema_data.py
dms_app/resources/settings/__init__.py
dms_app/resources/settings/person_autoincreament.py
dms_app/resources/truckMaster/__init__.py
dms_app/resources/truckMaster/check_list.py
dms_app/resources/truckMaster/check_list_master.py
dms_app/resources/truckMaster/truck_master.py
dms_app/resources/violation/__init__.py
dms_app/resources/violation/add_voilation.py
dms_app/resources/violation/person_violation.py
dms_app/router/__init__.py
DMS_APP-0.2.1.dist-info/METADATA
DMS_APP-0.2.1.dist-info/WHEEL
DMS_APP-0.2.1.dist-info/top_level.txt
DMS_APP-0.2.1.dist-info/RECORD
