Metadata-Version: 2.1
Name: DMS-APP
Version: 0.2.1
Summary: Driver Management System
Home-page: UNKNOWN
Author: Datamoulds
Author-email: Sachin@Datamoulds.com
License: UNKNOWN
Platform: UNKNOWN
Classifier: Programming Language :: Python :: 3
Classifier: License :: OSI Approved :: MIT License
Classifier: Operating System :: OS Independent
Requires-Python: >=3.8.8
